MANIFEST.in
setup.cfg
setup.py
Olympo.egg-info/PKG-INFO
Olympo.egg-info/SOURCES.txt
Olympo.egg-info/dependency_links.txt
Olympo.egg-info/requires.txt
Olympo.egg-info/top_level.txt
olympo/__init__.py
olympo/model/__init__.py
olympo/model/const_olympo.py
olympo/model/model.py
olympo/util/__init__.py
olympo/util/constantes.py
olympo/util/util.py