Metadata-Version: 1.0
Name: Olympo
Version: 0.0.3
Summary: A little set of utilities to manage Olympo projects
Home-page: http://www.ender.es
Author: León Domingo
Author-email: leon.domingo@ender.es
License: UNKNOWN
Keywords: ender olympo
Platform: UNKNOWN
Classifier: Development Status :: 5 - Production/Stable
Classifier: Topic :: Utilities
